[{"brand_id":"53","series_id":"75","series_name":"北斗星","auth_series_name":"北斗星"},{"brand_id":"53","series_id":"94","series_name":"羚羊","auth_series_name":"羚羊"},{"brand_id":"53","series_id":"362","series_name":"雨燕","auth_series_name":"雨燕"},{"brand_id":"53","series_id":"432","series_name":"利亚纳","auth_series_name":""},{"brand_id":"53","series_id":"500","series_name":"超级维特拉","auth_series_name":"维特拉"},{"brand_id":"53","series_id":"508","series_name":"吉姆尼","auth_series_name":"吉姆尼"},{"brand_id":"53","series_id":"529","series_name":"天语","auth_series_name":""},{"brand_id":"53","series_id":"872","series_name":"奥拓","auth_series_name":"奥拓"},{"brand_id":"53","series_id":"892","series_name":"凯泽西","auth_series_name":"凯泽西"},{"brand_id":"53","series_id":"2049","series_name":"派喜","auth_series_name":"派喜"},{"brand_id":"53","series_id":"2176","series_name":"速翼特","auth_series_name":"速翼特"},{"brand_id":"53","series_id":"2242","series_name":"天语","auth_series_name":""},{"brand_id":"53","series_id":"2534","series_name":"浪迪","auth_series_name":"浪迪"},{"brand_id":"53","series_id":"3112","series_name":"利亚纳A6","auth_series_name":""},{"brand_id":"53","series_id":"3185","series_name":"锋驭","auth_series_name":"锋驭"},{"brand_id":"53","series_id":"3216","series_name":"北斗星X5","auth_series_name":"北斗星X5"},{"brand_id":"53","series_id":"3528","series_name":"启悦","auth_series_name":""}]