[{"brand_id":"71","series_id":"163","series_name":"赛欧","auth_series_name":"赛欧"},{"brand_id":"71","series_id":"397","series_name":"景程","auth_series_name":"景程"},{"brand_id":"71","series_id":"420","series_name":"乐骋","auth_series_name":"乐骋"},{"brand_id":"71","series_id":"439","series_name":"乐风","auth_series_name":"乐风"},{"brand_id":"71","series_id":"546","series_name":"科帕奇(进口)","auth_series_name":"科帕奇"},{"brand_id":"71","series_id":"657","series_name":"科鲁兹","auth_series_name":""},{"brand_id":"71","series_id":"678","series_name":"科迈罗Camaro","auth_series_name":""},{"brand_id":"71","series_id":"682","series_name":"沃蓝达Volt","auth_series_name":""},{"brand_id":"71","series_id":"808","series_name":"斯帕可SPARK","auth_series_name":""},{"brand_id":"71","series_id":"2313","series_name":"迈锐宝","auth_series_name":"迈锐宝"},{"brand_id":"71","series_id":"2348","series_name":"爱唯欧","auth_series_name":""},{"brand_id":"71","series_id":"2583","series_name":"科帕奇","auth_series_name":"科帕奇"},{"brand_id":"71","series_id":"3335","series_name":"TRAX创酷","auth_series_name":""},{"brand_id":"71","series_id":"100019","series_name":"子弹头","auth_series_name":""}]