{"returnCode":{"type":"S","code":"success","message":"success"},"carTypeList":[{"typeId":"2243","typeName":"\u9646\u98ceX5","typeLogo":"http:\/\/sc-img.oss-cn-beijing.aliyuncs.com\/eQLnVs.jpg"},{"typeId":"2244","typeName":"\u9646\u98ceX8","typeLogo":"http:\/\/sc-img.oss-cn-beijing.aliyuncs.com\/S4jUyJ.jpg"},{"typeId":"2245","typeName":"\u9646\u98ceX6","typeLogo":"http:\/\/sc-img.oss-cn-beijing.aliyuncs.com\/U6PPFl.jpg"},{"typeId":"2246","typeName":"\u9646\u98ceX9","typeLogo":"http:\/\/sc-img.oss-cn-beijing.aliyuncs.com\/M5FoL9.jpg"},{"typeId":"2247","typeName":"\u9646\u98ce\u98ce\u5c1a","typeLogo":"http:\/\/sc-img.oss-cn-beijing.aliyuncs.com\/tMvYRY.jpg"},{"typeId":"2248","typeName":"\u9646\u98ce\u98ce\u534e","typeLogo":"http:\/\/sc-img.oss-cn-beijing.aliyuncs.com\/atsdVq.jpg"},{"typeId":"2249","typeName":"\u9646\u98ceX7","typeLogo":"http:\/\/sc-img.oss-cn-beijing.aliyuncs.com\/QBfVJX.jpg"}]}