{"brandid":"132","brandname":"\u6d77\u9a6c","brandimg":"http:\/\/imgs.xin.com\/xin\/images\/brand-100\/b_132.png","brandename":"H","serie":[{"makename":"\u6d77\u9a6c\u6c7d\u8f66","serielist":[{"serieid":"60","seriename":"323","model":[{"year":"2002\u6b3e","modellist":[{"modelid":"30866","modelname":"2002\u6b3e 1.8 \u624b\u52a8 \u8212\u9002\u578b"},{"modelid":"30868","modelname":"2002\u6b3e 1.8 \u624b\u52a8 \u8c6a\u534e\u578b"},{"modelid":"90000131","modelname":"2002\u6b3e 1.8 \u81ea\u52a8 \u8c6a\u534e\u578b"}]},{"year":"2000\u6b3e","modellist":[{"modelid":"3762","modelname":"2000\u6b3e 1.3 \u624b\u52a8 \u8212\u9002\u578b"},{"modelid":"19219","modelname":"2000\u6b3e 1.3 \u624b\u52a8 \u8c6a\u534e\u578b"}]},{"year":"1998\u6b3e","modellist":[{"modelid":"19222","modelname":"1998\u6b3e 1.8 \u624b\u52a8"}]}]},{"serieid":"2738","seriename":"M3","model":[{"year":"2015\u6b3e","modellist":[{"modelid":"149987","modelname":"2015\u6b3e 1.5 \u81ea\u52a8 \u4e03\u5f69\u9886\u822a\u7248"},{"modelid":"149989","modelname":"2015\u6b3e 1.5 \u624b\u52a8 \u4e03\u5f69\u9886\u822a\u7248"},{"modelid":"156328","modelname":"2015\u6b3e 1.5 \u624b\u52a8 \u6807\u51c6\u578b"},{"modelid":"156329","modelname":"2015\u6b3e 1.5 \u624b\u52a8 \u7cbe\u82f1\u578b"},{"modelid":"156330","modelname":"2015\u6b3e 1.5 \u624b\u52a8 \u8212\u9002\u578b"},{"modelid":"156331","modelname":"2015\u6b3e 1.5 \u624b\u52a8 \u8c6a\u534e\u578b"},{"modelid":"156332","modelname":"2015\u6b3e 1.5 \u624b\u52a8 \u65d7\u8230\u578b"},{"modelid":"156333","modelname":"2015\u6b3e 1.5 \u81ea\u52a8 \u7cbe\u82f1\u578b"},{"modelid":"156334","modelname":"2015\u6b3e 1.5 \u81ea\u52a8 \u8212\u9002\u578b"},{"modelid":"156335","modelname":"2015\u6b3e 1.5 \u81ea\u52a8 \u65d7\u8230\u578b"},{"modelid":"158649","modelname":"2015\u6b3e 1.5 \u624b\u52a8 \u6807\u51c6\u5929\u7a97\u7248"},{"modelid":"158650","modelname":"2015\u6b3e 1.5 \u624b\u52a8 \u7cbe\u82f1\u5929\u7a97\u7248"},{"modelid":"158651","modelname":"2015\u6b3e 1.5 \u81ea\u52a8 \u7cbe\u82f1\u5929\u7a97\u7248"}]},{"year":"2014\u6b3e","modellist":[{"modelid":"137578","modelname":"2014\u6b3e 1.5 \u624b\u52a8 \u70ab\u5f69\u57fa\u672c\u578b"},{"modelid":"137579","modelname":"2014\u6b3e 1.5 \u624b\u52a8 \u70ab\u5f69\u6807\u51c6\u578b"},{"modelid":"137581","modelname":"2014\u6b3e 1.5 \u624b\u52a8 \u70ab\u5f69\u7cbe\u82f1\u578b"},{"modelid":"137583","modelname":"2014\u6b3e 1.5 \u624b\u52a8 \u70ab\u5f69\u8212\u9002\u578b"},{"modelid":"137586","modelname":"2014\u6b3e 1.5 \u624b\u52a8 \u70ab\u5f69\u8c6a\u534e\u578b"},{"modelid":"137587","modelname":"2014\u6b3e 1.5 \u624b\u52a8 \u70ab\u5f69\u65d7\u8230\u578b"},{"modelid":"137588","modelname":"2014\u6b3e 1.5 \u81ea\u52a8 \u70ab\u5f69\u65d7\u8230\u578b"},{"modelid":"138760","modelname":"2014\u6b3e 1.5 \u624b\u52a8 \u6807\u51c6\u578b"},{"modelid":"138761","modelname":"2014\u6b3e 1.5 \u624b\u52a8 \u7cbe\u82f1\u578b"},{"modelid":"138762","modelname":"2014\u6b3e 1.5 \u624b\u52a8 \u8212\u9002\u578b"},{"modelid":"138763","modelname":"2014\u6b3e 1.5 \u624b\u52a8 \u8c6a\u534e\u578b"},{"modelid":"138764","modelname":"2014\u6b3e 1.5 \u624b\u52a8 \u65d7\u8230\u578b"},{"modelid":"138765","modelname":"2014\u6b3e 1.5 \u81ea\u52a8 \u7cbe\u82f1\u578b"},{"modelid":"138766","modelname":"2014\u6b3e 1.5 \u81ea\u52a8 \u8212\u9002\u578b"},{"modelid":"138767","modelname":"2014\u6b3e 1.5 \u81ea\u52a8 \u65d7\u8230\u578b"},{"modelid":"157000","modelname":"2014\u6b3e 1.5 \u624b\u52a8 \u4e03\u5f69\u9886\u822a\u7248"}]},{"year":"2013\u6b3e","modellist":[{"modelid":"132170","modelname":"2013\u6b3e 1.5 \u624b\u52a8 \u57fa\u672c\u578b"},{"modelid":"132171","modelname":"2013\u6b3e 1.5 \u624b\u52a8 \u6807\u51c6\u578b"},{"modelid":"132172","modelname":"2013\u6b3e 1.5 \u624b\u52a8 \u7cbe\u82f1\u578b"},{"modelid":"132173","modelname":"2013\u6b3e 1.5 \u81ea\u52a8 \u7cbe\u82f1\u578b"},{"modelid":"132174","modelname":"2013\u6b3e 1.5 \u624b\u52a8 \u8212\u9002\u578b"},{"modelid":"132175","modelname":"2013\u6b3e 1.5 \u81ea\u52a8 \u8212\u9002\u578b"},{"modelid":"132176","modelname":"2013\u6b3e 1.5 \u624b\u52a8 \u8c6a\u534e\u578b"},{"modelid":"132177","modelname":"2013\u6b3e 1.5 \u81ea\u52a8 \u8c6a\u534e\u578b"},{"modelid":"132178","modelname":"2013\u6b3e 1.5 \u624b\u52a8 \u65d7\u8230\u578b"},{"modelid":"132179","modelname":"2013\u6b3e 1.5 \u81ea\u52a8 \u65d7\u8230\u578b"}]}]},{"serieid":"3141","seriename":"M6","model":[{"year":"2015\u6b3e","modellist":[{"modelid":"156690","modelname":"2015\u6b3e 1.5T \u624b\u52a8 \u4e50FUN\u578b"},{"modelid":"156691","modelname":"2015\u6b3e 1.5T \u624b\u52a8 \u9a6dFUN\u578b"},{"modelid":"156692","modelname":"2015\u6b3e 1.5T \u624b\u52a8 \u667aFUN\u578b"},{"modelid":"156693","modelname":"2015\u6b3e 1.5T \u624b\u52a8 \u777fFUN\u578b"},{"modelid":"156694","modelname":"2015\u6b3e 1.5T \u81ea\u52a8 \u9a6dFUN\u578b"},{"modelid":"156695","modelname":"2015\u6b3e 1.5T \u81ea\u52a8 \u667aFUN\u578b"},{"modelid":"156696","modelname":"2015\u6b3e 1.5T \u81ea\u52a8 \u777fFUN\u578b"}]}]},{"serieid":"2854","seriename":"M8","model":[{"year":"2015\u6b3e","modellist":[{"modelid":"152371","modelname":"2015\u6b3e 2.0 \u624b\u52a8 \u65f6\u5c1a\u578b"},{"modelid":"152372","modelname":"2015\u6b3e 2.0 \u81ea\u52a8 \u65f6\u5c1a\u578b"},{"modelid":"152385","modelname":"2015\u6b3e 1.8T \u81ea\u52a8 \u8212\u9002\u578b"},{"modelid":"152402","modelname":"2015\u6b3e 1.8T \u81ea\u52a8 \u8c6a\u534e\u578b"}]},{"year":"2014\u6b3e","modellist":[{"modelid":"139728","modelname":"2014\u6b3e 2.0 \u624b\u52a8 \u8212\u9002\u578b"},{"modelid":"139729","modelname":"2014\u6b3e 2.0 \u81ea\u52a8 \u8212\u9002\u578b"},{"modelid":"139730","modelname":"2014\u6b3e 2.0 \u81ea\u52a8 \u8c6a\u534e\u578b"}]}]},{"serieid":"2959","seriename":"S5","model":[{"year":"2015\u6b3e","modellist":[{"modelid":"150229","modelname":"2015\u6b3e 1.5T \u81ea\u52a8 \u667a\u70ab\u578b\u524d\u9a71"},{"modelid":"150230","modelname":"2015\u6b3e 1.5T \u81ea\u52a8 \u667a\u9a8b\u578b\u524d\u9a71"},{"modelid":"150232","modelname":"2015\u6b3e 1.5T \u81ea\u52a8 \u667a\u5c0a\u578b\u524d\u9a71"},{"modelid":"154914","modelname":"2015\u6b3e 1.6 \u624b\u52a8 \u667a\u5c1a\u578b\u524d\u9a71"},{"modelid":"154915","modelname":"2015\u6b3e 1.6 \u624b\u52a8 \u667a\u4e50\u578b\u524d\u9a71"},{"modelid":"154916","modelname":"2015\u6b3e 1.6 \u624b\u52a8 \u667a\u70ab\u578b\u524d\u9a71"},{"modelid":"154917","modelname":"2015\u6b3e 1.6 \u624b\u52a8 \u667a\u5c0a\u578b\u524d\u9a71"},{"modelid":"154918","modelname":"2015\u6b3e 1.6 \u624b\u52a8 \u667a\u81fb\u578b\u524d\u9a71"},{"modelid":"158808","modelname":"2015\u6b3e 1.5T \u624b\u52a8 \u8fd0\u52a8\u667a\u5c1a\u578b"},{"modelid":"158809","modelname":"2015\u6b3e 1.5T \u624b\u52a8 \u8fd0\u52a8\u667a\u70ab\u578b"},{"modelid":"158810","modelname":"2015\u6b3e 1.5T \u624b\u52a8 \u8fd0\u52a8\u667a\u9a8b\u578b"},{"modelid":"158811","modelname":"2015\u6b3e 1.5T \u624b\u52a8 \u8fd0\u52a8\u667a\u5c0a\u578b"}]},{"year":"2014\u6b3e","modellist":[{"modelid":"146877","modelname":"2014\u6b3e 1.6 \u624b\u52a8 \u667a\u5c1a\u578b\u524d\u9a71"},{"modelid":"146878","modelname":"2014\u6b3e 1.6 \u624b\u52a8 \u667a\u4e50\u578b\u524d\u9a71"},{"modelid":"146879","modelname":"2014\u6b3e 1.6 \u624b\u52a8 \u667a\u70ab\u578b\u524d\u9a71"},{"modelid":"146880","modelname":"2014\u6b3e 1.6 \u624b\u52a8 \u667a\u9a8b\u578b\u524d\u9a71"},{"modelid":"146881","modelname":"2014\u6b3e 1.6 \u624b\u52a8 \u667a\u5c0a\u578b\u524d\u9a71"},{"modelid":"146883","modelname":"2014\u6b3e 1.6 \u624b\u52a8 \u667a\u81fb\u578b\u524d\u9a71"}]}]},{"serieid":"2766","seriename":"S7","model":[{"year":"2015\u6b3e","modellist":[{"modelid":"142718","modelname":"2015\u6b3e 2.0 \u81ea\u52a8 \u667a\u4eab\u7248\u524d\u9a71"},{"modelid":"150603","modelname":"2015\u6b3e 2.0 \u81ea\u52a8 \u667a\u5c1a\u578b\u524d\u9a71"},{"modelid":"150605","modelname":"2015\u6b3e 2.0 \u81ea\u52a8 \u667a\u81fb\u578b\u524d\u9a71"},{"modelid":"150607","modelname":"2015\u6b3e 2.0 \u624b\u52a8 \u667a\u5c1a\u578b\u524d\u9a71"},{"modelid":"150608","modelname":"2015\u6b3e 2.0 \u624b\u52a8 \u667a\u4eab\u578b\u524d\u9a71"},{"modelid":"150609","modelname":"2015\u6b3e 2.0 \u624b\u52a8 \u667a\u81fb\u578b\u524d\u9a71"},{"modelid":"155042","modelname":"2015\u6b3e 2.0 \u624b\u52a8 \u631a\u7231\u7248\u524d\u9a71"},{"modelid":"157192","modelname":"2015\u6b3e 2.0 \u624b\u52a8 \u7eb5\u4eab\u578b\u524d\u9a71"},{"modelid":"157193","modelname":"2015\u6b3e 2.0 \u624b\u52a8 \u7eb5\u9a70\u578b\u524d\u9a71"},{"modelid":"157194","modelname":"2015\u6b3e 2.0 \u624b\u52a8 \u7eb5\u8058\u578b\u524d\u9a71"},{"modelid":"157195","modelname":"2015\u6b3e 2.0 \u81ea\u52a8 \u7eb5\u9a70\u578b\u524d\u9a71"},{"modelid":"157196","modelname":"2015\u6b3e 1.8T \u81ea\u52a8 \u7eb5\u9a70\u578b\u524d\u9a71"},{"modelid":"157197","modelname":"2015\u6b3e 1.8T \u81ea\u52a8 \u7eb5\u8058\u578b\u524d\u9a71"},{"modelid":"157198","modelname":"2015\u6b3e 1.8T \u81ea\u52a8 \u7eb5\u9886\u578b\u524d\u9a71"}]},{"year":"2013\u6b3e","modellist":[{"modelid":"133309","modelname":"2013\u6b3e 2.0 \u624b\u52a8 \u667a\u5c1a\u578b\u524d\u9a71"},{"modelid":"133315","modelname":"2013\u6b3e 2.0 \u81ea\u52a8 \u667a\u5c1a\u578b\u524d\u9a71"},{"modelid":"133317","modelname":"2013\u6b3e 2.0 \u81ea\u52a8 \u667a\u4eab\u7248\u524d\u9a71"},{"modelid":"133318","modelname":"2013\u6b3e 2.0 \u624b\u52a8 \u667a\u81fb\u578b\u524d\u9a71"},{"modelid":"133319","modelname":"2013\u6b3e 2.0 \u81ea\u52a8 \u667a\u81fb\u578b\u524d\u9a71"},{"modelid":"142724","modelname":"2013\u6b3e 2.0 \u624b\u52a8 \u667a\u4eab\u578b\u524d\u9a71"}]}]},{"serieid":"1783","seriename":"\u4e18\u6bd4\u7279","model":[{"year":"2015\u6b3e","modellist":[{"modelid":"156355","modelname":"2015\u6b3e 1.3 \u624b\u52a8 \u9752\u8471\u7248"},{"modelid":"156356","modelname":"2015\u6b3e 1.3 \u624b\u52a8 \u6e05\u65b0\u7248"},{"modelid":"156358","modelname":"2015\u6b3e 1.5 \u81ea\u52a8 \u6e05\u60a6\u7248"}]},{"year":"2013\u6b3e","modellist":[{"modelid":"135522","modelname":"2013\u6b3e 1.5 \u81ea\u52a8 \u7075\u52a8\u578b"},{"modelid":"146063","modelname":"2013\u6b3e 1.3 \u624b\u52a8 \u52b2\u9177\u578b"},{"modelid":"146064","modelname":"2013\u6b3e 1.3 \u624b\u52a8 \u7075\u60a6\u578b"},{"modelid":"146065","modelname":"2013\u6b3e 1.3 \u624b\u52a8 \u70ab\u9177\u578b"}]},{"year":"2012\u6b3e","modellist":[{"modelid":"110563","modelname":"2012\u6b3e 1.3 \u624b\u52a8 C-sport\u70ab\u9177\u578b"},{"modelid":"110564","modelname":"2012\u6b3e 1.3 \u624b\u52a8 C-sport\u52b2\u9177\u578b"},{"modelid":"110565","modelname":"2012\u6b3e 1.3 \u624b\u52a8 \u7075\u60a6\u578b"},{"modelid":"110566","modelname":"2012\u6b3e 1.5 \u81ea\u52a8 \u7075\u52a8\u578b"}]},{"year":"2011\u6b3e","modellist":[{"modelid":"103359","modelname":"2011\u6b3e 1.3 \u624b\u52a8 C-sport"},{"modelid":"103360","modelname":"2011\u6b3e 1.3 \u624b\u52a8 GLX\u8212\u9002\u578b"},{"modelid":"103361","modelname":"2011\u6b3e 1.3 \u624b\u52a8 GL\u57fa\u672c\u578b"},{"modelid":"103362","modelname":"2011\u6b3e 1.5 \u81ea\u52a8 DX\u8212\u9002\u578b"}]},{"year":"2010\u6b3e","modellist":[{"modelid":"38746","modelname":"2010\u6b3e 1.3 \u624b\u52a8 \u5b9e\u7528\u578b"},{"modelid":"38747","modelname":"2010\u6b3e 1.3 \u624b\u52a8 \u8212\u9002\u578b"},{"modelid":"40203","modelname":"2010\u6b3e 1.3 \u624b\u52a8 \u8c6a\u534e\u578b"},{"modelid":"40221","modelname":"2010\u6b3e 1.5 \u624b\u52a8 \u8c6a\u534e\u578b"},{"modelid":"58461","modelname":"2010\u6b3e 1.5 \u624b\u52a8 sports"},{"modelid":"132846","modelname":"2010\u6b3e 1.5 \u81ea\u52a8 \u8212\u9002\u578b"},{"modelid":"132847","modelname":"2010\u6b3e 1.5 \u81ea\u52a8 \u5b9e\u7528\u578b"},{"modelid":"132848","modelname":"2010\u6b3e 1.5 \u81ea\u52a8 sports"}]}]},{"serieid":"61","seriename":"\u65c5\u884c\u8f66","model":[{"year":"1998\u6b3e","modellist":[{"modelid":"19418","modelname":"1998\u6b3e 2.5 \u81ea\u52a8 7\u5ea7"}]}]},{"serieid":"305","seriename":"\u666e\u529b\u9a6c","model":[{"year":"2014\u6b3e","modellist":[{"modelid":"138755","modelname":"2014\u6b3e 1.6 \u624b\u52a8 \u521b\u60f3\u72487\u5ea7"},{"modelid":"138756","modelname":"2014\u6b3e 1.6 \u624b\u52a8 \u5f00\u62d3\u72487\u5ea7"},{"modelid":"138757","modelname":"2014\u6b3e 1.6 \u81ea\u52a8 \u4e50\u4eab\u72487\u5ea7"},{"modelid":"138758","modelname":"2014\u6b3e 1.8 \u81ea\u52a8 \u5c0a\u4eab\u72487\u5ea7"}]},{"year":"2013\u6b3e","modellist":[{"modelid":"132695","modelname":"2013\u6b3e 1.6 \u81ea\u52a8 \u4e50\u4eab\u72487\u5ea7"},{"modelid":"132696","modelname":"2013\u6b3e 1.8 \u81ea\u52a8 \u5c0a\u4eab\u72487\u5ea7"},{"modelid":"148500","modelname":"2013\u6b3e 1.6 \u624b\u52a8 \u521b\u60f3\u72487\u5ea7"},{"modelid":"148501","modelname":"2013\u6b3e 1.6 \u624b\u52a8 \u8fdb\u53d6\u72487\u5ea7"},{"modelid":"148502","modelname":"2013\u6b3e 1.6 \u624b\u52a8 \u5f00\u62d3\u72487\u5ea7"}]},{"year":"2011\u6b3e","modellist":[{"modelid":"62148","modelname":"2011\u6b3e 1.6 \u81ea\u52a8 \u8212\u9002\u578b5\u5ea7"},{"modelid":"103336","modelname":"2011\u6b3e 1.6 \u81ea\u52a8 \u70ab\u9177\u578b5\u5ea7"},{"modelid":"103337","modelname":"2011\u6b3e 1.6 \u624b\u52a8 \u521b\u60f3\u578b7\u5ea7"},{"modelid":"103339","modelname":"2011\u6b3e 1.6 \u624b\u52a8 \u5f00\u62d3\u578b7\u5ea7"},{"modelid":"103340","modelname":"2011\u6b3e 1.6 \u624b\u52a8 \u8212\u9002\u578b5\u5ea7"},{"modelid":"103341","modelname":"2011\u6b3e 1.6 \u624b\u52a8 \u70ab\u52a8\u578b5\u5ea7"},{"modelid":"103343","modelname":"2011\u6b3e 1.8 \u81ea\u52a8 \u5c0a\u4eab\u578b7\u5ea7"},{"modelid":"157287","modelname":"2011\u6b3e 1.8 \u624b\u52a8 \u521b\u60f3\u578b7\u5ea7"}]},{"year":"2010\u6b3e","modellist":[{"modelid":"32323","modelname":"2010\u6b3e 1.6 \u624b\u52a8 \u57fa\u672c\u578b5\u5ea7"},{"modelid":"32324","modelname":"2010\u6b3e 1.6 \u624b\u52a8 \u8c6a\u534e\u578b5\u5ea7"},{"modelid":"32325","modelname":"2010\u6b3e 1.8 \u81ea\u52a8 \u8212\u9002\u578b5\u5ea7"},{"modelid":"32326","modelname":"2010\u6b3e 1.8 \u81ea\u52a8 \u8c6a\u534e\u578b7\u5ea7"},{"modelid":"58475","modelname":"2010\u6b3e 1.6 \u624b\u52a8 \u8212\u9002\u578b5\u5ea7"},{"modelid":"58476","modelname":"2010\u6b3e 1.6 \u624b\u52a8 \u8c6a\u534e\u578b7\u5ea7"},{"modelid":"113365","modelname":"2010\u6b3e 5\u5ea7 \u7eaf\u7535\u52a8"},{"modelid":"148809","modelname":"2010\u6b3e 1.6 \u81ea\u52a8 \u8212\u9002\u578b5\u5ea7"}]},{"year":"2007\u6b3e","modellist":[{"modelid":"11698","modelname":"2007\u6b3e 1.8 \u81ea\u52a8 STD\u6807\u51c6\u578b5\u5ea7"},{"modelid":"11699","modelname":"2007\u6b3e 1.8 \u624b\u52a8 GL\u6807\u51c6\u578b5\u5ea7"},{"modelid":"11700","modelname":"2007\u6b3e 1.8 \u624b\u52a8 GLX\u8212\u9002\u578b5\u5ea7"},{"modelid":"11701","modelname":"2007\u6b3e 1.8 \u81ea\u52a8 SDX\u8c6a\u534e\u578b5\u5ea7"},{"modelid":"11702","modelname":"2007\u6b3e 1.8 \u624b\u52a8 GLS\u8c6a\u534e\u578b7\u5ea7"}]},{"year":"2006\u6b3e","modellist":[{"modelid":"3295","modelname":"2006\u6b3e 1.8 \u624b\u52a8 GLX\u8212\u9002\u578b5\u5ea7"},{"modelid":"19433","modelname":"2006\u6b3e 1.8 \u624b\u52a8 GLS\u8c6a\u534e\u578b7\u5ea7"},{"modelid":"19434","modelname":"2006\u6b3e 1.8 \u624b\u52a8 GL\u6807\u51c6\u578b5\u5ea7"},{"modelid":"19440","modelname":"2006\u6b3e 1.8 \u81ea\u52a8 SDX\u8c6a\u534e\u578b5\u5ea7"},{"modelid":"19441","modelname":"2006\u6b3e 1.8 \u81ea\u52a8 STD\u6807\u51c6\u578b5\u5ea7"},{"modelid":"90000083","modelname":"2006\u6b3e 1.8 \u81ea\u52a8 DX\u8212\u9002\u578b7\u5ea7"}]},{"year":"2005\u6b3e","modellist":[{"modelid":"3290","modelname":"2005\u6b3e 1.8 \u81ea\u52a8 DX\u8212\u9002\u578b5\u5ea7"},{"modelid":"3291","modelname":"2005\u6b3e 1.8 \u81ea\u52a8 SDX\u8c6a\u534e\u578b5\u5ea7"}]},{"year":"2004\u6b3e","modellist":[{"modelid":"3269","modelname":"2004\u6b3e 1.8 \u81ea\u52a8 DX\u8212\u9002\u578b5\u5ea7"},{"modelid":"3270","modelname":"2004\u6b3e 1.8 \u81ea\u52a8 SDX\u8c6a\u534e\u578b7\u5ea7"},{"modelid":"3273","modelname":"2004\u6b3e 1.8 \u624b\u52a8 GL\u6807\u51c6\u578b5\u5ea7"},{"modelid":"3274","modelname":"2004\u6b3e 1.8 \u624b\u52a8 GLX\u8212\u9002\u578b5\u5ea7"},{"modelid":"3276","modelname":"2004\u6b3e 1.8 \u81ea\u52a8 DX\u8212\u9002\u578b7\u5ea7"},{"modelid":"3277","modelname":"2004\u6b3e 1.8 \u81ea\u52a8 SDX\u8c6a\u534e\u578b5\u5ea7"},{"modelid":"19430","modelname":"2004\u6b3e 1.8 \u624b\u52a8 GL\u6807\u51c6\u578b7\u5ea7"},{"modelid":"19431","modelname":"2004\u6b3e 1.8 \u624b\u52a8 GLS\u8212\u9002\u578b7\u5ea7"}]},{"year":"2003\u6b3e","modellist":[{"modelid":"3265","modelname":"2003\u6b3e 1.8 \u624b\u52a8 \u8fd0\u52a8\u578b5\u5ea7"},{"modelid":"3268","modelname":"2003\u6b3e 1.8 \u81ea\u52a8 \u65f6\u5c1a\u578b7\u5ea7"},{"modelid":"3278","modelname":"2003\u6b3e 1.8 \u81ea\u52a8 \u65d7\u8230\u578b7\u5ea7"},{"modelid":"3793","modelname":"2003\u6b3e 1.8 \u81ea\u52a8 DX\u8212\u9002\u578b7\u5ea7"},{"modelid":"19429","modelname":"2003\u6b3e 1.8 \u81ea\u52a8 DX\u8212\u9002\u578b5\u5ea7"}]},{"year":"2002\u6b3e","modellist":[{"modelid":"3781","modelname":"2002\u6b3e 1.8 \u81ea\u52a8 SDX\u8c6a\u534e\u578b7\u5ea7"},{"modelid":"19427","modelname":"2002\u6b3e 1.8 \u81ea\u52a8 SDX\u8c6a\u534e\u578b5\u5ea7"}]},{"year":"2001\u6b3e","modellist":[{"modelid":"3790","modelname":"2001\u6b3e 1.8 \u624b\u52a8 GL\u6807\u51c6\u578b7\u5ea7"},{"modelid":"19426","modelname":"2001\u6b3e 1.8 \u624b\u52a8 GL\u6807\u51c6\u578b5\u5ea7"},{"modelid":"25708","modelname":"2001\u6b3e 1.8 \u81ea\u52a8 SDX\u8c6a\u534e\u578b7\u5ea7"}]}]},{"serieid":"611","seriename":"\u6b22\u52a8","model":[{"year":"2010\u6b3e","modellist":[{"modelid":"103326","modelname":"2010\u6b3e 1.6 \u81ea\u52a8 \u8212\u9002\u578b"},{"modelid":"103327","modelname":"2010\u6b3e 1.6 \u81ea\u52a8 \u8fd0\u52a8\u578b"},{"modelid":"103328","modelname":"2010\u6b3e 1.6 \u624b\u52a8 \u8212\u9002\u578b"},{"modelid":"103329","modelname":"2010\u6b3e 1.6 \u624b\u52a8 \u8fd0\u52a8\u578b"}]},{"year":"2009\u6b3e","modellist":[{"modelid":"13273","modelname":"2009\u6b3e 1.8 \u624b\u52a8 GLX\u8212\u9002\u578b"},{"modelid":"13274","modelname":"2009\u6b3e 1.8 \u81ea\u52a8 GLX\u8212\u9002\u578b"},{"modelid":"13275","modelname":"2009\u6b3e 1.8 \u624b\u52a8 GLS\u8c6a\u534e\u578b"},{"modelid":"13276","modelname":"2009\u6b3e 1.8 \u81ea\u52a8 GLS\u8c6a\u534e\u578b"},{"modelid":"21752","modelname":"2009\u6b3e 1.6 \u624b\u52a8 \u6807\u51c6\u578b"},{"modelid":"21753","modelname":"2009\u6b3e 1.6 \u624b\u52a8 \u8212\u9002\u578b"},{"modelid":"21754","modelname":"2009\u6b3e 1.6 \u624b\u52a8 \u8c6a\u534e\u578b"},{"modelid":"27814","modelname":"2009\u6b3e 1.6 \u81ea\u52a8 \u8c6a\u534e\u578b"}]}]},{"serieid":"207","seriename":"\u6d77\u798f\u661f","model":[{"year":"2012\u6b3e","modellist":[{"modelid":"111318","modelname":"2012\u6b3e 1.5 \u624b\u52a8 \u7cbe\u82f1\u578b"},{"modelid":"111319","modelname":"2012\u6b3e 1.5 \u624b\u52a8 \u5c0a\u8d35\u578b"}]},{"year":"2011\u6b3e","modellist":[{"modelid":"103293","modelname":"2011\u6b3e 1.3 \u624b\u52a8 \u8c6a\u534e\u578b"},{"modelid":"103294","modelname":"2011\u6b3e 1.3 \u624b\u52a8 \u8212\u9002\u578b"}]},{"year":"2010\u6b3e","modellist":[{"modelid":"58451","modelname":"2010\u6b3e 1.6 \u624b\u52a8 GL\u6807\u51c6\u578b"},{"modelid":"108773","modelname":"2010\u6b3e 1.3 \u624b\u52a8 \u8212\u9002\u578b"},{"modelid":"108774","modelname":"2010\u6b3e 1.5 \u624b\u52a8 \u7cbe\u82f1\u578b"},{"modelid":"108776","modelname":"2010\u6b3e 1.6 \u624b\u52a8"},{"modelid":"108777","modelname":"2010\u6b3e 1.6 \u624b\u52a8 CNG\u6cb9\u6c14\u6df7\u5408"},{"modelid":"136864","modelname":"2010\u6b3e 1.6 \u624b\u52a8 GLX\u8212\u9002\u5929\u7a97\u578b"}]},{"year":"2009\u6b3e","modellist":[{"modelid":"11230","modelname":"2009\u6b3e 1.6 \u624b\u52a8 GX\u5e78\u798f\u7248"},{"modelid":"42325","modelname":"2009\u6b3e 1.6 \u624b\u52a8 GLX\u8212\u9002\u578b"},{"modelid":"61426","modelname":"2009\u6b3e 1.6 \u624b\u52a8 CNG\u6cb9\u6c14\u6df7\u5408"},{"modelid":"61427","modelname":"2009\u6b3e 1.6 \u624b\u52a8 \u6cb9\u6c14\u6df7\u5408"},{"modelid":"61431","modelname":"2009\u6b3e 1.6 \u624b\u52a8 \u8fdb\u53e3\u53d1\u52a8\u673a"},{"modelid":"136862","modelname":"2009\u6b3e 1.6 \u624b\u52a8 GL\u6807\u51c6\u578b"}]},{"year":"2008\u6b3e","modellist":[{"modelid":"42364","modelname":"2008\u6b3e 1.6 \u624b\u52a8 CNG\u6cb9\u6c14\u6df7\u5408"},{"modelid":"61429","modelname":"2008\u6b3e 1.6 \u624b\u52a8"}]},{"year":"2007\u6b3e","modellist":[{"modelid":"11693","modelname":"2007\u6b3e 1.6 \u624b\u52a8 GL\u6807\u51c6\u578b"},{"modelid":"11694","modelname":"2007\u6b3e 1.6 \u624b\u52a8 GLS\u8c6a\u534e\u578b"},{"modelid":"11695","modelname":"2007\u6b3e 1.6 \u624b\u52a8 GLX\u8212\u9002\u578b"}]},{"year":"2006\u6b3e","modellist":[{"modelid":"75004","modelname":"2006\u6b3e 1.6 \u624b\u52a8"}]}]},{"serieid":"197","seriename":"\u6d77\u9a6c3","model":[{"year":"2010\u6b3e","modellist":[{"modelid":"103313","modelname":"2010\u6b3e 1.6 \u624b\u52a8 GLX\u5929\u7a97\u578b"},{"modelid":"103315","modelname":"2010\u6b3e 1.6 \u81ea\u52a8 SDX\u8c6a\u534e\u578b"}]},{"year":"2008\u6b3e","modellist":[{"modelid":"10300","modelname":"2008\u6b3e 1.8 \u624b\u52a8 \u8fd0\u52a8\u7248"}]},{"year":"2007\u6b3e","modellist":[{"modelid":"11696","modelname":"2007\u6b3e 1.8 \u624b\u52a8 GL\u6807\u51c6\u578b"},{"modelid":"11697","modelname":"2007\u6b3e 1.8 \u624b\u52a8 GLS\u8c6a\u534e\u578b"}]}]},{"serieid":"2976","seriename":"\u798f\u7f8e\u6765M5","model":[{"year":"2015\u6b3e","modellist":[{"modelid":"155157","modelname":"2015\u6b3e 1.6 \u624b\u52a8 \u631a\u7231\u7248"}]},{"year":"2014\u6b3e","modellist":[{"modelid":"147158","modelname":"2014\u6b3e 1.6 \u624b\u52a8 \u6807\u51c6\u578b"},{"modelid":"147160","modelname":"2014\u6b3e 1.6 \u624b\u52a8 \u7cbe\u82f1\u578b"},{"modelid":"147162","modelname":"2014\u6b3e 1.6 \u624b\u52a8 \u8212\u9002\u578b"},{"modelid":"147164","modelname":"2014\u6b3e 1.6 \u624b\u52a8 \u65f6\u5c1a\u578b"},{"modelid":"147166","modelname":"2014\u6b3e 1.6 \u624b\u52a8 \u8c6a\u534e\u578b"},{"modelid":"147168","modelname":"2014\u6b3e 1.6 \u624b\u52a8 \u5c0a\u8d35\u578b"},{"modelid":"147170","modelname":"2014\u6b3e 1.6 \u81ea\u52a8 \u7cbe\u82f1\u578b"},{"modelid":"147172","modelname":"2014\u6b3e 1.6 \u81ea\u52a8 \u8212\u9002\u578b"},{"modelid":"147174","modelname":"2014\u6b3e 1.6 \u81ea\u52a8 \u5c0a\u8d35\u578b"}]}]},{"serieid":"303","seriename":"\u798f\u7f8e\u6765\u4e09\u53a2","model":[{"year":"2015\u6b3e","modellist":[{"modelid":"148968","modelname":"2015\u6b3e 1.6 \u624b\u52a8 \u65f6\u5c1a\u7248"},{"modelid":"148969","modelname":"2015\u6b3e 1.6 \u624b\u52a8 \u8c6a\u534e\u7248"},{"modelid":"148970","modelname":"2015\u6b3e 1.6 \u624b\u52a8 \u51a0\u519b\u7248"},{"modelid":"154680","modelname":"2015\u6b3e 1.6 \u624b\u52a8 \u7cbe\u82f1\u7248"},{"modelid":"154681","modelname":"2015\u6b3e 1.6 \u624b\u52a8 \u5929\u7a97\u7248"},{"modelid":"157212","modelname":"2015\u6b3e 1.6 \u624b\u52a8 \u98ce\u5c1a\u578b"},{"modelid":"157213","modelname":"2015\u6b3e 1.6 \u624b\u52a8 \u54c1\u5c1a\u578b"},{"modelid":"157214","modelname":"2015\u6b3e 1.6 \u624b\u52a8 \u60a6\u5c1a\u578b"},{"modelid":"157215","modelname":"2015\u6b3e 1.6 \u624b\u52a8 \u667a\u5c1a\u578b"},{"modelid":"157216","modelname":"2015\u6b3e 1.6 \u81ea\u52a8 \u98ce\u5c1a\u578b"},{"modelid":"157217","modelname":"2015\u6b3e 1.6 \u81ea\u52a8 \u54c1\u5c1a\u578b"},{"modelid":"157218","modelname":"2015\u6b3e 1.5T \u81ea\u52a8 \u54c1\u5c1a\u578b"},{"modelid":"157219","modelname":"2015\u6b3e 1.5T \u81ea\u52a8 \u60a6\u5c1a\u578b"},{"modelid":"157220","modelname":"2015\u6b3e 1.5T \u81ea\u52a8 \u884c\u653f\u5c0a\u5c1a\u578b"}]},{"year":"2014\u6b3e","modellist":[{"modelid":"156893","modelname":"2014\u6b3e 1.6 \u624b\u52a8 \u51a0\u519b\u7248"},{"modelid":"156894","modelname":"2014\u6b3e 1.6 \u624b\u52a8 \u8c6a\u534e\u7248"},{"modelid":"156895","modelname":"2014\u6b3e 1.6 \u624b\u52a8 \u65f6\u5c1a\u7248"}]},{"year":"2013\u6b3e","modellist":[{"modelid":"122168","modelname":"2013\u6b3e 1.6 \u624b\u52a8 \u51a0\u519b\u7248"},{"modelid":"142620","modelname":"2013\u6b3e 1.6 \u624b\u52a8 \u98ce\u5c1a\u7248"},{"modelid":"142621","modelname":"2013\u6b3e 1.6 \u624b\u52a8 \u7cbe\u82f1\u7248"},{"modelid":"142622","modelname":"2013\u6b3e 1.6 \u624b\u52a8 \u65d7\u8230\u7248"},{"modelid":"142624","modelname":"2013\u6b3e 1.6 \u81ea\u52a8 \u7cbe\u82f1\u7248"},{"modelid":"142626","modelname":"2013\u6b3e 1.6 \u81ea\u52a8 \u65d7\u8230\u7248"}]},{"year":"2012\u6b3e","modellist":[{"modelid":"108631","modelname":"2012\u6b3e 1.6 \u624b\u52a8 \u98ce\u5c1a\u7248"},{"modelid":"108632","modelname":"2012\u6b3e 1.6 \u81ea\u52a8 \u98ce\u5c1a\u7248"},{"modelid":"108633","modelname":"2012\u6b3e 1.6 \u624b\u52a8 \u7cbe\u82f1\u7248"},{"modelid":"108634","modelname":"2012\u6b3e 1.6 \u81ea\u52a8 \u7cbe\u82f1\u7248"},{"modelid":"108635","modelname":"2012\u6b3e 1.6 \u624b\u52a8 \u65d7\u8230\u7248"},{"modelid":"108636","modelname":"2012\u6b3e 1.6 \u81ea\u52a8 \u65d7\u8230\u7248"},{"modelid":"138118","modelname":"2012\u6b3e 1.6 \u81ea\u52a8 CNG\u6cb9\u6c14\u6df7\u5408"}]},{"year":"2011\u6b3e","modellist":[{"modelid":"61595","modelname":"2011\u6b3e 1.6 \u624b\u52a8 8\u5468\u5e74\u7eaa\u5ff5\u578b"},{"modelid":"61596","modelname":"2011\u6b3e 1.6 \u81ea\u52a8 8\u5468\u5e74\u7eaa\u5ff5\u578b"},{"modelid":"103253","modelname":"2011\u6b3e 1.6 \u81ea\u52a8 \u8c6a\u534e\u578b\u4e09\u4ee3"},{"modelid":"103254","modelname":"2011\u6b3e 1.6 \u81ea\u52a8 \u8212\u9002\u578b\u4e09\u4ee3"},{"modelid":"103255","modelname":"2011\u6b3e 1.6 \u81ea\u52a8 \u5b9c\u5c45\u7248\u4e09\u4ee3"},{"modelid":"103281","modelname":"2011\u6b3e 1.6 \u624b\u52a8 \u8c6a\u534e\u578b\u4e09\u4ee3"},{"modelid":"103282","modelname":"2011\u6b3e 1.6 \u624b\u52a8 \u8212\u9002\u578b\u4e09\u4ee3"},{"modelid":"103283","modelname":"2011\u6b3e 1.6 \u624b\u52a8 \u5b9c\u5c45\u7248\u4e09\u4ee3"}]},{"year":"2010\u6b3e","modellist":[{"modelid":"58455","modelname":"2010\u6b3e 1.6 \u624b\u52a8 \u8212\u9002\u578b"},{"modelid":"58456","modelname":"2010\u6b3e 1.6 \u624b\u52a8 \u8c6a\u534e\u578b"},{"modelid":"58457","modelname":"2010\u6b3e 1.6 \u81ea\u52a8 \u8212\u9002\u578b"}]},{"year":"2009\u6b3e","modellist":[{"modelid":"25697","modelname":"2009\u6b3e 1.6 \u81ea\u52a8 \u8d85\u503c\u578b"},{"modelid":"25698","modelname":"2009\u6b3e 1.6 \u624b\u52a8 \u8d85\u503c\u578b"}]},{"year":"2008\u6b3e","modellist":[{"modelid":"11861","modelname":"2008\u6b3e 1.6 \u624b\u52a8 GLX\u8212\u9002\u578b"},{"modelid":"11862","modelname":"2008\u6b3e 1.6 \u624b\u52a8 GLS\u8c6a\u534e\u578b"},{"modelid":"11863","modelname":"2008\u6b3e 1.6 \u81ea\u52a8 DX\u8212\u9002\u578b"},{"modelid":"11864","modelname":"2008\u6b3e 1.6 \u81ea\u52a8 SDX\u8c6a\u534e\u578b"}]},{"year":"2007\u6b3e","modellist":[{"modelid":"11690","modelname":"2007\u6b3e 1.6 \u81ea\u52a8 DX\u8212\u9002\u578b"},{"modelid":"11691","modelname":"2007\u6b3e 1.6 \u624b\u52a8 GLX\u8212\u9002\u578b"},{"modelid":"11692","modelname":"2007\u6b3e 1.6 \u81ea\u52a8 SDX\u8c6a\u534e\u578b"},{"modelid":"17163","modelname":"2007\u6b3e 1.6 \u81ea\u52a8 STD\u6807\u51c6\u578b"},{"modelid":"17170","modelname":"2007\u6b3e 1.6 \u81ea\u52a8 DX\u8c6a\u534e\u578b"},{"modelid":"17171","modelname":"2007\u6b3e 1.6 \u624b\u52a8 DX\u8c6a\u534e\u578b"},{"modelid":"17172","modelname":"2007\u6b3e 1.6 \u624b\u52a8 DX\u8212\u9002\u578b"},{"modelid":"109730","modelname":"2007\u6b3e 1.6 \u624b\u52a8 GL\u6807\u51c6\u578b"},{"modelid":"109731","modelname":"2007\u6b3e 1.6 \u624b\u52a8 GLS\u8c6a\u534e\u578b"},{"modelid":"109733","modelname":"2007\u6b3e 1.6 \u624b\u52a8 GX\u666e\u901a\u578b"}]},{"year":"2006\u6b3e","modellist":[{"modelid":"5353","modelname":"2006\u6b3e 1.6 \u624b\u52a8 \u8fd0\u52a8\u578b"},{"modelid":"17185","modelname":"2006\u6b3e 1.6 \u624b\u52a8 GL\u6807\u51c6\u578b"},{"modelid":"17186","modelname":"2006\u6b3e 1.6 \u624b\u52a8 GLS\u8c6a\u534e\u578b"},{"modelid":"17187","modelname":"2006\u6b3e 1.6 \u624b\u52a8 GX\u666e\u901a\u578b"},{"modelid":"17188","modelname":"2006\u6b3e 1.6 \u81ea\u52a8 SDX\u8c6a\u534e\u578b"},{"modelid":"17189","modelname":"2006\u6b3e 1.6 \u81ea\u52a8 STD\u6807\u51c6\u578b"}]},{"year":"2005\u6b3e","modellist":[{"modelid":"440","modelname":"2005\u6b3e 1.6 \u624b\u52a8 \u65b0\u9510\u578b"},{"modelid":"3794","modelname":"2005\u6b3e 1.6 \u81ea\u52a8 \u8212\u9002\u578b"},{"modelid":"3795","modelname":"2005\u6b3e 1.6 \u624b\u52a8 \u8212\u9002\u578b"},{"modelid":"3796","modelname":"2005\u6b3e 1.6 \u624b\u52a8 \u8c6a\u534e\u578b"},{"modelid":"3798","modelname":"2005\u6b3e 1.6 \u81ea\u52a8 \u8c6a\u534e\u578b"},{"modelid":"17175","modelname":"2005\u6b3e 1.6 \u624b\u52a8 GL\u6807\u51c6\u578b"},{"modelid":"17177","modelname":"2005\u6b3e 1.6 \u624b\u52a8 GLS\u8c6a\u534e\u578b"},{"modelid":"17179","modelname":"2005\u6b3e 1.6 \u624b\u52a8 GX\u666e\u901a\u578b"},{"modelid":"17181","modelname":"2005\u6b3e 1.6 \u81ea\u52a8 SDX\u8c6a\u534e\u578b"},{"modelid":"17183","modelname":"2005\u6b3e 1.6 \u81ea\u52a8 STD\u6807\u51c6\u578b"}]},{"year":"2004\u6b3e","modellist":[{"modelid":"874","modelname":"2004\u6b3e 1.6 \u624b\u52a8 \u65b0\u60a6\u578b"},{"modelid":"875","modelname":"2004\u6b3e 1.8 \u81ea\u52a8 \u7cbe\u82f1\u578b\u5929\u7a97\u7248"},{"modelid":"3312","modelname":"2004\u6b3e 1.8 \u81ea\u52a8 \u7cbe\u82f1\u578b"},{"modelid":"3313","modelname":"2004\u6b3e 1.8 \u81ea\u52a8 \u5c0a\u8d35\u578b"},{"modelid":"3317","modelname":"2004\u6b3e 1.6 \u624b\u52a8 \u65b0\u8d35\u578b"},{"modelid":"3326","modelname":"2004\u6b3e 1.8 \u81ea\u52a8 \u5c0a\u8363\u578b"},{"modelid":"17190","modelname":"2004\u6b3e 1.6 \u624b\u52a8 \u6807\u51c6\u578b"}]},{"year":"2003\u6b3e","modellist":[{"modelid":"3299","modelname":"2003\u6b3e 1.6 \u624b\u52a8 \u6807\u51c6\u578b"},{"modelid":"3305","modelname":"2003\u6b3e 1.8 \u81ea\u52a8 \u7cbe\u82f1\u578b"}]},{"year":"2002\u6b3e","modellist":[{"modelid":"3301","modelname":"2002\u6b3e 1.8 \u81ea\u52a8 \u7cbe\u82f1\u578b"},{"modelid":"3303","modelname":"2002\u6b3e 1.8 \u81ea\u52a8 \u5c0a\u8d35\u578b"}]}]},{"serieid":"2502","seriename":"\u798f\u7f8e\u6765\u4e24\u53a2","model":[{"year":"2012\u6b3e","modellist":[{"modelid":"108652","modelname":"2012\u6b3e 1.6 \u624b\u52a8 \u98ce\u5c1a\u7248"},{"modelid":"108653","modelname":"2012\u6b3e 1.6 \u81ea\u52a8 \u98ce\u5c1a\u7248"},{"modelid":"108654","modelname":"2012\u6b3e 1.6 \u624b\u52a8 \u7cbe\u82f1\u7248"},{"modelid":"108655","modelname":"2012\u6b3e 1.6 \u81ea\u52a8 \u7cbe\u82f1\u7248"},{"modelid":"108656","modelname":"2012\u6b3e 1.6 \u624b\u52a8 \u65d7\u8230\u7248"},{"modelid":"108657","modelname":"2012\u6b3e 1.6 \u81ea\u52a8 \u65d7\u8230\u7248"}]}]},{"serieid":"1927","seriename":"\u9a91\u58eb","model":[{"year":"2013\u6b3e","modellist":[{"modelid":"116870","modelname":"2013\u6b3e 2.0 \u81ea\u52a8 \u90fd\u5e02\u7cbe\u82f1\u7248"},{"modelid":"136866","modelname":"2013\u6b3e 2.0 \u624b\u52a8 \u5178\u96c5\u98ce\u5c1a\u578b"},{"modelid":"136867","modelname":"2013\u6b3e 2.0 \u624b\u52a8 \u90fd\u5e02\u7cbe\u82f1\u578b"},{"modelid":"136868","modelname":"2013\u6b3e 2.0 \u624b\u52a8 \u667a\u80fd\u9886\u822a\u578b"},{"modelid":"136869","modelname":"2013\u6b3e 2.0 \u81ea\u52a8 \u5178\u96c5\u98ce\u5c1a\u578b"},{"modelid":"136870","modelname":"2013\u6b3e 2.0 \u81ea\u52a8 \u667a\u80fd\u9886\u822a\u578b"},{"modelid":"150960","modelname":"2013\u6b3e 2.0 \u624b\u52a8 \u7ecf\u5178\u578b"}]},{"year":"2012\u6b3e","modellist":[{"modelid":"103318","modelname":"2012\u6b3e 2.0 \u81ea\u52a8 \u5178\u96c5\u98ce\u5c1a\u578b"},{"modelid":"103319","modelname":"2012\u6b3e 2.0 \u81ea\u52a8 \u667a\u80fd\u9886\u822a\u578b"},{"modelid":"103320","modelname":"2012\u6b3e 2.0 \u624b\u52a8 \u5178\u96c5\u98ce\u5c1a\u578b"},{"modelid":"103321","modelname":"2012\u6b3e 2.0 \u624b\u52a8 \u90fd\u5e02\u7cbe\u82f1\u578b"},{"modelid":"103322","modelname":"2012\u6b3e 2.0 \u624b\u52a8 \u667a\u80fd\u9886\u822a\u578b"}]},{"year":"2011\u6b3e","modellist":[{"modelid":"132582","modelname":"2011\u6b3e 2.0 \u624b\u52a8 \u4e1d\u8def\u9650\u91cf\u7eaa\u5ff5\u7248"}]},{"year":"2010\u6b3e","modellist":[{"modelid":"132580","modelname":"2010\u6b3e 2.0 \u624b\u52a8 \u667a\u80fd\u9886\u822a\u578b"},{"modelid":"132584","modelname":"2010\u6b3e 2.0 \u624b\u52a8 \u90fd\u5e02\u7cbe\u82f1\u578b"}]}]}]},{"makename":"\u6d77\u9a6c\u90d1\u5dde","serielist":[{"serieid":"2491","seriename":"\u7231\u5c1a","model":[{"year":"2012\u6b3e","modellist":[{"modelid":"138169","modelname":"2012\u6b3e 1.0 \u624b\u52a8 \u57fa\u672c\u578b"},{"modelid":"138172","modelname":"2012\u6b3e 1.0 \u624b\u52a8 \u6807\u51c6\u578b"},{"modelid":"138173","modelname":"2012\u6b3e 1.0 \u624b\u52a8 \u8212\u9002\u578b"},{"modelid":"138177","modelname":"2012\u6b3e 1.0 \u624b\u52a8 \u8c6a\u534e\u578b"},{"modelid":"148698","modelname":"2012\u6b3e 1.2 \u624b\u52a8 \u8c6a\u534e\u578b"},{"modelid":"148699","modelname":"2012\u6b3e 1.2 \u81ea\u52a8 \u8212\u9002\u578b"}]}]},{"serieid":"1973","seriename":"\u738b\u5b50","model":[{"year":"2011\u6b3e","modellist":[{"modelid":"103384","modelname":"2011\u6b3e 1.0 \u624b\u52a8 \u8c6a\u534e\u578b"},{"modelid":"103385","modelname":"2011\u6b3e 1.0 \u624b\u52a8 \u57fa\u672c\u578b"},{"modelid":"103386","modelname":"2011\u6b3e 1.0 \u624b\u52a8 \u7ecf\u6d4e\u578b"},{"modelid":"103388","modelname":"2011\u6b3e 1.0 \u624b\u52a8 \u8212\u9002\u578b"}]},{"year":"2010\u6b3e","modellist":[{"modelid":"59107","modelname":"2010\u6b3e 1.0 \u624b\u52a8 \u7ecf\u6d4e\u578b"},{"modelid":"59108","modelname":"2010\u6b3e 1.0 \u624b\u52a8 \u6807\u51c6\u578b"},{"modelid":"59109","modelname":"2010\u6b3e 1.0 \u624b\u52a8 \u5b9e\u529b\u578b"},{"modelid":"59110","modelname":"2010\u6b3e 1.0 \u624b\u52a8 \u8fdb\u53d6\u578b"},{"modelid":"59111","modelname":"2010\u6b3e 1.0 \u624b\u52a8 \u7cbe\u82f1\u578b"}]},{"year":"2009\u6b3e","modellist":[{"modelid":"75005","modelname":"2009\u6b3e 1.0 \u624b\u52a8"}]}]},{"serieid":"2024","seriename":"\u798f\u4ed5\u8fbe","model":[{"year":"2014\u6b3e","modellist":[{"modelid":"147122","modelname":"2014\u6b3e 1.2 \u624b\u52a8 \u8c6a\u534e\u578b7\u5ea7"},{"modelid":"147123","modelname":"2014\u6b3e 1.2 \u624b\u52a8 \u8c6a\u534e\u578b8\u5ea7"},{"modelid":"147124","modelname":"2014\u6b3e 1.2 \u624b\u52a8 \u8c6a\u534e\u578b5\u5ea7"},{"modelid":"147125","modelname":"2014\u6b3e 1.2 \u624b\u52a8 \u6807\u51c6\u578b7\u5ea7"},{"modelid":"147126","modelname":"2014\u6b3e 1.2 \u624b\u52a8 \u6807\u51c6\u578b8\u5ea7"},{"modelid":"147127","modelname":"2014\u6b3e 1.2 \u624b\u52a8 \u6807\u51c6\u578b5\u5ea7"}]},{"year":"2013\u6b3e","modellist":[{"modelid":"136525","modelname":"2013\u6b3e 1.2 \u624b\u52a8 \u6807\u51c6\u578b7\u5ea7"},{"modelid":"136526","modelname":"2013\u6b3e 1.2 \u624b\u52a8 \u8212\u9002\u578b7\u5ea7"},{"modelid":"136527","modelname":"2013\u6b3e 1.2 \u624b\u52a8 \u8c6a\u534e\u578b7\u5ea7"},{"modelid":"136528","modelname":"2013\u6b3e 1.2 \u624b\u52a8 \u65d7\u8230\u578b7\u5ea7"}]},{"year":"2012\u6b3e","modellist":[{"modelid":"136500","modelname":"2012\u6b3e 1.2 \u624b\u52a8 \u6807\u51c6\u578b7\u5ea7"},{"modelid":"136501","modelname":"2012\u6b3e 1.2 \u624b\u52a8 \u8c6a\u534e\u578b7\u5ea7"},{"modelid":"136515","modelname":"2012\u6b3e 1.0 \u624b\u52a8 \u5b9e\u7528\u578b7\u5ea7"},{"modelid":"142967","modelname":"2012\u6b3e 1.2 \u624b\u52a8 \u5b9e\u7528\u578b7\u5ea7"}]},{"year":"2011\u6b3e","modellist":[{"modelid":"103371","modelname":"2011\u6b3e 1.0 \u624b\u52a8 \u8d85\u503c\u578b"},{"modelid":"138279","modelname":"2011\u6b3e 1.0 \u624b\u52a8 \u6807\u51c6\u578b7\u5ea7"},{"modelid":"138280","modelname":"2011\u6b3e 1.0 \u624b\u52a8 \u8c6a\u534e\u578b7\u5ea7"}]},{"year":"2010\u6b3e","modellist":[{"modelid":"103374","modelname":"2010\u6b3e 1.0 \u624b\u52a8 \u5b9e\u7528\u578b"}]},{"year":"2009\u6b3e","modellist":[{"modelid":"103370","modelname":"2009\u6b3e 1.0 \u624b\u52a8 \u6807\u51c6\u578b"},{"modelid":"103372","modelname":"2009\u6b3e 1.0 \u624b\u52a8 \u8c6a\u534e\u578b"},{"modelid":"103375","modelname":"2009\u6b3e 1.0 \u624b\u52a8 \u8212\u9002\u578b"},{"modelid":"136455","modelname":"2009\u6b3e 1.0 \u624b\u52a8 \u8d85\u503c\u578b7\u5ea7"},{"modelid":"136456","modelname":"2009\u6b3e 1.0 \u624b\u52a8 \u5b9e\u7528\u578b7\u5ea7"},{"modelid":"136457","modelname":"2009\u6b3e 1.0 \u624b\u52a8 \u6807\u51c6\u578b7\u5ea7"},{"modelid":"136458","modelname":"2009\u6b3e 1.0 \u624b\u52a8 \u8212\u9002\u578b7\u5ea7"},{"modelid":"136459","modelname":"2009\u6b3e 1.0 \u624b\u52a8 \u8c6a\u534e\u578b7\u5ea7"},{"modelid":"138224","modelname":"2009\u6b3e 1.0 \u624b\u52a8 \u8d85\u503c\u7248"},{"modelid":"138225","modelname":"2009\u6b3e 1.0 \u624b\u52a8 \u5b9e\u7528\u578b"},{"modelid":"138252","modelname":"2009\u6b3e 1.0 \u624b\u52a8 \u8d85\u503c\u578b\u6539\u6b3e"}]}]}]}]}