{"head":{"returnCode":"000","returnDescription":"\u9a8c\u8bc1\u901a\u8fc7","sysTime":"2015-10-31 19:47:38"},"body":{"series_detail":[{"model_id":"1001592","model_name":"2011\u6b3e 2.4L\u6c7d\u6cb9\u4e24\u9a71YZK1030E1","market_price":"11.98"},{"model_id":"1001593","model_name":"2011\u6b3e 2.4L\u6c7d\u6cb9\u56db\u9a71YZK1030E1S","market_price":"14.68"},{"model_id":"1001594","model_name":"2011\u6b3e 2.5T\u67f4\u6cb9\u4e24\u9a71DK4A","market_price":"14.18"},{"model_id":"1001595","model_name":"2011\u6b3e 2.5T\u67f4\u6cb9\u56db\u9a71DK4A","market_price":"15.98"},{"model_id":"1002086","model_name":"2014\u6b3e 2.4L\u6c7d\u6cb9\u4e24\u9a714G69S4N","market_price":"11.98"},{"model_id":"1002087","model_name":"2014\u6b3e 2.4L\u6c7d\u6cb9\u56db\u9a714G69S4N","market_price":"14.68"},{"model_id":"1002088","model_name":"2014\u6b3e 2.5T\u67f4\u6cb9\u4e24\u9a71DK4B","market_price":"14.68"},{"model_id":"1002089","model_name":"2014\u6b3e 2.5T\u67f4\u6cb9\u56db\u9a71DK4B","market_price":"16.48"}],"result":"0","description":"\u83b7\u5f97\u8f66\u578b\u4fe1\u606f"}}