{"head":{"returnCode":"000","returnDescription":"\u9a8c\u8bc1\u901a\u8fc7","sysTime":"2015-10-31 19:32:49"},"body":{"series_detail":[{"model_id":"6270","model_name":"2010\u6b3e 1.6L \u624b\u52a8\u5b9e\u7528\u578b","market_price":"7.48"},{"model_id":"6271","model_name":"2010\u6b3e 1.6L \u624b\u52a8\u8212\u9002\u578b","market_price":"7.98"},{"model_id":"6272","model_name":"2010\u6b3e 1.6L \u624b\u52a8\u8c6a\u534e\u578b","market_price":"8.48"},{"model_id":"8973","model_name":"2011\u6b3e 1.6L \u624b\u52a8\u5546\u7528\u578b5\u5ea7","market_price":"6.98"},{"model_id":"9427","model_name":"2011\u6b3e 1.6L \u624b\u52a8\u5b9e\u7528\u578b7\u5ea7","market_price":"7.83"},{"model_id":"9428","model_name":"2011\u6b3e 1.6L \u624b\u52a8\u8212\u9002\u578b7\u5ea7","market_price":"8.33"},{"model_id":"9429","model_name":"2011\u6b3e 1.6L \u624b\u52a8\u8c6a\u534e\u578b7\u5ea7","market_price":"8.73"},{"model_id":"10795","model_name":"2011\u6b3e 2.0L \u624b\u52a8\u8212\u9002\u578b7\u5ea7","market_price":"9.18"},{"model_id":"10825","model_name":"2011\u6b3e 2.0L \u624b\u52a8\u8c6a\u534e\u578b7\u5ea7","market_price":"9.48"},{"model_id":"11026","model_name":"2011\u6b3e 1.5L \u624b\u52a8\u6807\u51c6\u578b7\u5ea7 \u56fdIV","market_price":"6.68"},{"model_id":"11027","model_name":"2011\u6b3e 1.5L \u624b\u52a8\u8212\u9002\u578b7\u5ea7 \u56fdIV","market_price":"6.98"},{"model_id":"12383","model_name":"2012\u6b3e 2.0L \u81ea\u52a8\u8c6a\u534e\u578b7\u5ea7","market_price":"10.78"},{"model_id":"12566","model_name":"2012\u6b3e 2.0L \u81ea\u52a8\u65d7\u8230\u578b7\u5ea7","market_price":"11.58"},{"model_id":"13454","model_name":"2011\u6b3e 1.5L \u624b\u52a8\u6807\u51c6\u578b5\u5ea7 \u56fdIV","market_price":"6.38"},{"model_id":"15396","model_name":"2013\u6b3e 1.5L \u624b\u52a8\u6807\u51c6\u578b5\u5ea7 \u56fdV","market_price":"6.48"},{"model_id":"15397","model_name":"2013\u6b3e 1.5L \u624b\u52a8\u6807\u51c6\u578b7\u5ea7 \u56fdV","market_price":"6.78"},{"model_id":"15398","model_name":"2013\u6b3e 1.5L \u624b\u52a8\u8212\u9002\u578b7\u5ea7 \u56fdV","market_price":"7.18"},{"model_id":"17272","model_name":"2013\u6b3e \u6539\u6b3e 1.5L \u624b\u52a8\u6807\u51c6\u578b5\u5ea7 \u56fdIV","market_price":"6.38"},{"model_id":"17273","model_name":"2013\u6b3e \u6539\u6b3e 1.5L \u624b\u52a8\u6807\u51c6\u578b7\u5ea7 \u56fdIV","market_price":"6.68"},{"model_id":"17274","model_name":"2013\u6b3e \u6539\u6b3e 1.5L \u624b\u52a8\u8212\u9002\u578b7\u5ea7 \u56fdIV","market_price":"7.18"},{"model_id":"17275","model_name":"2013\u6b3e \u6539\u6b3e 1.5L \u624b\u52a8\u8c6a\u534e\u578b7\u5ea7 \u56fdIV","market_price":"7.38"},{"model_id":"17276","model_name":"2013\u6b3e \u6539\u6b3e 1.5L \u624b\u52a8\u6807\u51c6\u578b5\u5ea7 \u56fdV","market_price":"6.48"},{"model_id":"17277","model_name":"2013\u6b3e \u6539\u6b3e 1.5L \u624b\u52a8\u6807\u51c6\u578b7\u5ea7 \u56fdV","market_price":"6.78"},{"model_id":"17278","model_name":"2013\u6b3e \u6539\u6b3e 1.5L \u624b\u52a8\u8212\u9002\u578b7\u5ea7 \u56fdV","market_price":"7.28"},{"model_id":"17279","model_name":"2013\u6b3e \u6539\u6b3e 1.5L \u624b\u52a8\u8c6a\u534e\u578b7\u5ea7 \u56fdV","market_price":"7.48"},{"model_id":"17341","model_name":"2013\u6b3e \u6539\u6b3e 1.6L \u624b\u52a8\u5546\u7528\u578b5\u5ea7 \u56fdV","market_price":"7.08"},{"model_id":"17342","model_name":"2013\u6b3e \u6539\u6b3e 1.6L \u624b\u52a8\u5b9e\u7528\u578b7\u5ea7 \u56fdV","market_price":"7.83"},{"model_id":"17343","model_name":"2013\u6b3e \u6539\u6b3e 1.6L \u624b\u52a8\u8212\u9002\u578b7\u5ea7 \u56fdV","market_price":"8.33"},{"model_id":"17344","model_name":"2013\u6b3e \u6539\u6b3e 1.6L \u624b\u52a8\u8c6a\u534e\u578b7\u5ea7 \u56fdV","market_price":"8.73"},{"model_id":"19599","model_name":"2014\u6b3e 1.5L \u624b\u52a8\u6807\u51c6\u578b5\u5ea7 \u56fdIV","market_price":"6.48"},{"model_id":"19600","model_name":"2014\u6b3e 1.5L \u624b\u52a8\u6807\u51c6\u578b5\u5ea7 \u56fdV","market_price":"6.58"},{"model_id":"19601","model_name":"2014\u6b3e 1.5L \u624b\u52a8\u6807\u51c6\u578b7\u5ea7 \u56fdIV","market_price":"6.78"},{"model_id":"19602","model_name":"2014\u6b3e 1.5L \u624b\u52a8\u6807\u51c6\u578b7\u5ea7 \u56fdV","market_price":"6.88"},{"model_id":"19603","model_name":"2014\u6b3e 1.6L \u624b\u52a8\u8c6a\u534e\u578b7\u5ea7 \u56fdIV","market_price":"9.18"},{"model_id":"19604","model_name":"2014\u6b3e 1.6L \u624b\u52a8\u8212\u9002\u578b7\u5ea7 \u56fdIV","market_price":"8.68"},{"model_id":"19605","model_name":"2014\u6b3e 1.6L \u624b\u52a8\u8212\u9002\u578b7\u5ea7 \u56fdV","market_price":"8.68"},{"model_id":"19606","model_name":"2014\u6b3e 1.6L \u624b\u52a8\u8c6a\u534e\u578b7\u5ea7 \u56fdV","market_price":"9.18"}],"result":"0","description":"\u83b7\u5f97\u8f66\u578b\u4fe1\u606f"}}