{"head":{"returnCode":"000","returnDescription":"\u9a8c\u8bc1\u901a\u8fc7","sysTime":"2015-10-31 19:34:44"},"body":{"series_detail":[{"model_id":"8437","model_name":"2011\u6b3e 2.0L \u624b\u52a8\u6807\u51c6\u578b","market_price":"6.98"},{"model_id":"8438","model_name":"2011\u6b3e 2.0L \u624b\u52a8\u5b9e\u7528\u578b","market_price":"7.48"},{"model_id":"8439","model_name":"2011\u6b3e 2.0L \u624b\u52a8\u8212\u9002\u578b","market_price":"7.98"},{"model_id":"8440","model_name":"2011\u6b3e 2.0L \u624b\u52a8\u7cbe\u82f1\u578b","market_price":"9.98"},{"model_id":"8441","model_name":"2011\u6b3e 2.0L \u81ea\u52a8\u6807\u51c6\u578b","market_price":"7.98"},{"model_id":"8442","model_name":"2011\u6b3e 2.0L \u81ea\u52a8\u5b9e\u7528\u578b","market_price":"8.48"},{"model_id":"8443","model_name":"2011\u6b3e 2.0L \u81ea\u52a8\u8212\u9002\u578b","market_price":"8.98"},{"model_id":"8444","model_name":"2011\u6b3e 2.0L \u81ea\u52a8\u7cbe\u82f1\u578b","market_price":"10.98"},{"model_id":"8445","model_name":"2011\u6b3e 2.4L \u81ea\u52a8\u6807\u51c6\u578b","market_price":"8.48"},{"model_id":"8446","model_name":"2011\u6b3e 2.4L \u81ea\u52a8\u5b9e\u7528\u578b","market_price":"8.98"},{"model_id":"8447","model_name":"2011\u6b3e 2.4L \u81ea\u52a8\u8212\u9002\u578b","market_price":"9.48"},{"model_id":"8448","model_name":"2011\u6b3e 2.4L \u81ea\u52a8\u7cbe\u82f1\u578b","market_price":"11.48"},{"model_id":"9801","model_name":"2011\u6b3e 2.0L \u624b\u52a8\u8c6a\u534e\u578b","market_price":"8.58"},{"model_id":"9802","model_name":"2011\u6b3e 2.0L \u81ea\u52a8\u8c6a\u534e\u578b","market_price":"9.58"},{"model_id":"9803","model_name":"2011\u6b3e 2.4L \u81ea\u52a8\u8c6a\u534e\u578b","market_price":"10.08"},{"model_id":"12622","model_name":"2012\u6b3e 1.5T \u624b\u52a8\u5b9e\u5c1a\u578b","market_price":"7.99"},{"model_id":"12623","model_name":"2012\u6b3e 1.5T \u624b\u52a8\u96c5\u5c1a\u578b","market_price":"8.79"},{"model_id":"12624","model_name":"2012\u6b3e 1.5T \u624b\u52a8\u5c0a\u5c1a\u578b","market_price":"10.29"},{"model_id":"16310","model_name":"2013\u6b3e 1.5T \u624b\u52a8\u5b9e\u5c1a\u578b","market_price":"7.99"},{"model_id":"16311","model_name":"2013\u6b3e 1.5T \u624b\u52a8\u96c5\u5c1a\u578b","market_price":"8.79"},{"model_id":"16312","model_name":"2013\u6b3e 1.5T \u624b\u52a8\u5c0a\u5c1a\u578b","market_price":"10.29"},{"model_id":"16313","model_name":"2013\u6b3e 2.0L \u81ea\u52a8\u8212\u9002\u578b","market_price":"8.98"},{"model_id":"16314","model_name":"2013\u6b3e 2.4L \u81ea\u52a8\u8212\u9002\u578b","market_price":"9.48"},{"model_id":"16315","model_name":"2013\u6b3e 2.4L \u81ea\u52a8\u7cbe\u82f1\u578b","market_price":"0"}],"result":"0","description":"\u83b7\u5f97\u8f66\u578b\u4fe1\u606f"}}