{"head":{"returnCode":"000","returnDescription":"\u9a8c\u8bc1\u901a\u8fc7","sysTime":"2015-10-31 19:35:09"},"body":{"series_detail":[{"model_id":"9758","model_name":"2012\u6b3e 1.6L \u81ea\u52a8\u8c6a\u534e\u578b","market_price":"12.98"},{"model_id":"11395","model_name":"2012\u6b3e 1.6L \u624b\u52a8\u8212\u9002\u578b","market_price":"10.98"},{"model_id":"11396","model_name":"2012\u6b3e 1.6L \u624b\u52a8\u8c6a\u534e\u578b","market_price":"11.98"},{"model_id":"11397","model_name":"2012\u6b3e 1.6L \u81ea\u52a8\u8212\u9002\u578b","market_price":"11.98"},{"model_id":"11398","model_name":"2012\u6b3e 1.6L \u81ea\u52a8\u5c0a\u8d35\u578b","market_price":"14.58"},{"model_id":"12640","model_name":"2012\u6b3e 1.5T \u81ea\u52a8\u56db\u9a71\u5c0a\u8d35\u578b","market_price":"16.58"},{"model_id":"13424","model_name":"2012\u6b3e 1.5T \u624b\u52a8\u4e24\u9a71\u8fd0\u52a8\u578b","market_price":"11.98"},{"model_id":"13425","model_name":"2012\u6b3e 1.5T \u624b\u52a8\u4e24\u9a71\u8c6a\u534e\u578b","market_price":"12.58"},{"model_id":"13426","model_name":"2012\u6b3e 1.5T \u81ea\u52a8\u4e24\u9a71\u8fd0\u52a8\u578b","market_price":"12.98"},{"model_id":"13427","model_name":"2012\u6b3e 1.5T \u81ea\u52a8\u4e24\u9a71\u8c6a\u534e\u578b","market_price":"13.78"},{"model_id":"13428","model_name":"2012\u6b3e 1.5T \u81ea\u52a8\u4e24\u9a71\u5c0a\u8d35\u578b","market_price":"15.58"},{"model_id":"13429","model_name":"2012\u6b3e 1.5T \u81ea\u52a8\u56db\u9a71\u8c6a\u534e\u578b","market_price":"14.78"},{"model_id":"19022","model_name":"2014\u6b3e 1.5T \u81ea\u52a8\u4e24\u9a71\u8c6a\u534e\u578b","market_price":"11.78"},{"model_id":"20054","model_name":"2014\u6b3e 1.6L \u624b\u52a8\u8212\u9002\u578b","market_price":"8.98"},{"model_id":"20055","model_name":"2014\u6b3e 1.6L \u624b\u52a8\u8c6a\u534e\u578b","market_price":"9.98"},{"model_id":"20056","model_name":"2014\u6b3e 1.6L \u81ea\u52a8\u8212\u9002\u578b","market_price":"9.98"},{"model_id":"20057","model_name":"2014\u6b3e 1.6L \u81ea\u52a8\u8c6a\u534e\u578b","market_price":"10.98"},{"model_id":"20058","model_name":"2014\u6b3e 1.5T \u624b\u52a8\u4e24\u9a71\u8fd0\u52a8\u578b","market_price":"9.98"},{"model_id":"20059","model_name":"2014\u6b3e 1.5T \u624b\u52a8\u4e24\u9a71\u8c6a\u534e\u578b","market_price":"10.58"},{"model_id":"20060","model_name":"2014\u6b3e 1.5T \u81ea\u52a8\u4e24\u9a71\u8fd0\u52a8\u578b","market_price":"10.98"},{"model_id":"20061","model_name":"2014\u6b3e 1.5T \u81ea\u52a8\u56db\u9a71\u8c6a\u534e\u578b","market_price":"12.78"},{"model_id":"20062","model_name":"2014\u6b3e 1.5T \u81ea\u52a8\u56db\u9a71\u5c0a\u8d35\u578b","market_price":"14.58"}],"result":"0","description":"\u83b7\u5f97\u8f66\u578b\u4fe1\u606f"}}