{"head":{"returnCode":"000","returnDescription":"\u9a8c\u8bc1\u901a\u8fc7","sysTime":"2015-10-31 19:43:34"},"body":{"series_detail":[{"model_id":"1000375","model_name":"2010\u6b3e 2.4L\u4e24\u9a71\u6c7d\u6cb9\u8c6a\u534e\u578b\u77ed\u8f74","market_price":"7.98"},{"model_id":"1000376","model_name":"2010\u6b3e 2.4L\u4e24\u9a71\u6c7d\u6cb9\u8c6a\u534e\u578b\u957f\u8f74","market_price":"8.18"},{"model_id":"1000379","model_name":"2010\u6b3e 2.4L\u56db\u9a71\u6c7d\u6cb9\u8c6a\u534e\u578b\u77ed\u8f74","market_price":"9.48"},{"model_id":"1000380","model_name":"2010\u6b3e 2.4L\u56db\u9a71\u6c7d\u6cb9\u8c6a\u534e\u578b\u957f\u8f74","market_price":"9.68"},{"model_id":"1000396","model_name":"2010\u6b3e 2.8T\u6d77\u5916\u7248\u4e24\u9a71\u67f4\u6cb9\u8c6a\u534e\u578b","market_price":"8.03"},{"model_id":"1000397","model_name":"2010\u6b3e 3.0T\u6d77\u5916\u7248\u56db\u9a71\u67f4\u6cb9\u8c6a\u534e\u578b","market_price":"9.78"},{"model_id":"1000872","model_name":"2011\u6b3e 2.4L-F1 \u4e24\u9a71\u6c7d\u6cb9\u57fa\u672c\u578b","market_price":"8.18"},{"model_id":"1000873","model_name":"2011\u6b3e 2.8T-F1 \u4e24\u9a71\u67f4\u6cb9\u57fa\u672c\u578b","market_price":"8.18"},{"model_id":"1000874","model_name":"2011\u6b3e 2.4L-F1 \u56db\u9a71\u6c7d\u6cb9\u57fa\u672c\u578b","market_price":"9.68"},{"model_id":"1001128","model_name":"2010\u6b3e 2.5T\u4e24\u9a71\u67f4\u6cb9\u57fa\u672c\u578b","market_price":"9.88"},{"model_id":"1001539","model_name":"2013\u6b3e 2.8T\u67f4\u6cb9\u4e24\u9a71\u5171\u8f68","market_price":"8.33"},{"model_id":"1001616","model_name":"2013\u6b3e 2.8T\u67f4\u6cb9\u4e24\u9a71VE\u6cf5","market_price":"7.18"},{"model_id":"1001617","model_name":"2013\u6b3e 2.4L\u6c7d\u6cb9\u4e24\u9a71\u7cbe\u82f1\u578b","market_price":"8.08"},{"model_id":"1001821","model_name":"2013\u6b3e 2.4L\u6c7d\u6cb9\u56db\u9a71\u7cbe\u82f1\u578b","market_price":"9.08"},{"model_id":"1001921","model_name":"2013\u6b3e 2.5T\u67f4\u6cb9\u4e24\u9a71\u8c6a\u534e\u578b\u5171\u8f68","market_price":"8.98"},{"model_id":"1001922","model_name":"2013\u6b3e 2.5T\u67f4\u6cb9\u56db\u9a71\u8c6a\u534e\u578b\u5171\u8f68","market_price":"10.28"},{"model_id":"1002084","model_name":"2014\u6b3e 2.5T\u67f4\u6cb9\u4e24\u9a71\u8c6a\u534e\u578b","market_price":"9.08"},{"model_id":"1002085","model_name":"2014\u6b3e 2.5T\u67f4\u6cb9\u56db\u9a71\u8c6a\u534e\u578b","market_price":"10.38"},{"model_id":"1002606","model_name":"2014\u6b3e 2.2L\u6c7d\u6cb9\u4e24\u9a71\u7cbe\u82f1\u578b","market_price":"7.08"},{"model_id":"1002607","model_name":"2014\u6b3e 2.2L\u6c7d\u6cb9\u56db\u9a71\u7cbe\u82f1\u578b","market_price":"8.38"},{"model_id":"1003170","model_name":"2014\u6b3e 2.8T\u4e24\u9a71\u67f4\u6cb9\u7cbe\u82f1\u578b","market_price":"7.88"},{"model_id":"1003171","model_name":"2014\u6b3e 2.8T\u4e24\u9a71\u67f4\u6cb9\u8c6a\u534e\u578b","market_price":"8.68"},{"model_id":"1003172","model_name":"2014\u6b3e 2.8T\u56db\u9a71\u67f4\u6cb9\u8c6a\u534e\u578b","market_price":"9.68"}],"result":"0","description":"\u83b7\u5f97\u8f66\u578b\u4fe1\u606f"}}