{"head":{"returnCode":"000","returnDescription":"\u9a8c\u8bc1\u901a\u8fc7","sysTime":"2015-10-31 19:52:17"},"body":{"series_detail":[{"model_id":"18385","model_name":"2014\u6b3e 1.6L \u624b\u52a8\u5c0a\u5c1a\u7248","market_price":"8.59"},{"model_id":"19126","model_name":"2014\u6b3e 1.6L \u624b\u52a8\u98ce\u5c1a\u7248","market_price":"7.39"},{"model_id":"19127","model_name":"2014\u6b3e 1.6L \u624b\u52a8\u667a\u5c1a\u7248","market_price":"7.79"},{"model_id":"19128","model_name":"2014\u6b3e 1.6L CVT\u98ce\u5c1a\u7248","market_price":"8.39"},{"model_id":"19129","model_name":"2014\u6b3e 1.6L CVT\u667a\u5c1a\u7248","market_price":"8.79"},{"model_id":"19130","model_name":"2014\u6b3e 1.6L CVT\u5c0a\u5c1a\u7248","market_price":"9.59"},{"model_id":"20117","model_name":"2014\u6b3e \u9b54\u529b\u7248 1.6L CVT\u5c0a\u5c1a\u7248","market_price":"9.89"},{"model_id":"21132","model_name":"2014\u6b3e \u9b54\u529b\u7248 1.6L \u624b\u52a8\u98ce\u5c1a\u7248","market_price":"7.39"},{"model_id":"21133","model_name":"2014\u6b3e \u9b54\u529b\u7248 1.6L \u624b\u52a8\u667a\u5c1a\u7248","market_price":"8.09"},{"model_id":"21134","model_name":"2014\u6b3e \u9b54\u529b\u7248 1.6L \u624b\u52a8\u5c0a\u5c1a\u7248","market_price":"8.89"},{"model_id":"21135","model_name":"2014\u6b3e \u9b54\u529b\u7248 1.6L CVT\u98ce\u5c1a\u7248","market_price":"8.39"},{"model_id":"21136","model_name":"2014\u6b3e \u9b54\u529b\u7248 1.6L CVT\u667a\u5c1a\u7248","market_price":"9.09"}],"result":"0","description":"\u83b7\u5f97\u8f66\u578b\u4fe1\u606f"}}